[
  {
    "missle": [
        {
            "unit_id": "1",
            "name": "Grunggson's Boast",
            "range": "18",
            "attacks": "2",
            "to_hit": "3",
            "to_wound": "2",
            "rend": "-1",
            "damage": "D3"
        },
        {
            "unit_id": "1",
            "name": "Magnate's Charter",
            "range": "18",
            "attacks": "3",
            "to_hit": "3",
            "to_wound": "3",
            "rend": "-1",
            "damage": "1"
        },
        {
            "unit_id": "1",
            "name": "Aetherblasters saw",
            "range": "9",
            "attacks": "2",
            "to_hit": "3",
            "to_wound": "4",
            "rend": "-",
            "damage": "1"
        }
    ]
  }
]
